RealPass/__init__.py
realpass-0.6.dist-info/METADATA
realpass-0.6.dist-info/WHEEL
realpass-0.6.dist-info/license.md
realpass-0.6.dist-info/top_level.txt
realpass-0.6.dist-info/RECORD
